awstuff
