Metadata-Version: 2.1
Name: awstuff
Version: 0.211
Summary: Helper functions for interacting with AWS and other misc tasks
Home-page: UNKNOWN
Author-email: danieldbrickell@gmail.com
License: UNKNOWN
Platform: UNKNOWN
